{
  "project_info": {
    "project_number": "376489192496",
    "project_id": "todolist-3299a",
    "storage_bucket": "todolist-3299a.appspot.com"
  },
  "client": [
    {
      "client_info": {
        "mobilesdk_app_id": "1:376489192496:android:a4c907aab397a267d651f5",
        "android_client_info": {
          "package_name": "com.example.todo_list"
        }
      },
      "oauth_client": [],
      "api_key": [
        {
          "current_key": "AIzaSyCyKKQNPWRH_-9AIkyvJdSUpNUZVRJmmtI"
        }
      ],
      "services": {
        "appinvite_service": {
          "other_platform_oauth_client": []
        }
      }
    }
  ],
  "configuration_version": "1"
}